[
    {
        "type": "text",
        "text": "DOI:10.5846/stxb201701090066 ",
        "text_level": 1,
        "page_idx": 0
    },
    {
        "type": "text",
        "text": "吴文广,张继红,刘毅,王巍,蔺凡.獐子岛及邻近海域秋季浮游植物的粒级结构及其影响因素.生态学报,2018,38（4);1418-1426.WuWG,ZagJnginfctoedadisctoagdddcwaters.Acta Ecologica Sinica,2018,38(4) :1418-1426.",
        "page_idx": 0
    },
    {
        "type": "text",
        "text": "獐子岛及邻近海域秋季浮游植物的粒级结构及其影响因素",
        "text_level": 1,
        "page_idx": 0
    },
    {
        "type": "text",
        "text": "吴文广¹，张继红1,2，\\*，刘毅¹，王 巍¹,蔺凡1",
        "page_idx": 0
    },
    {
        "type": "text",
        "text": "1中国水产科学研究院黄海水产研究所，农业部海洋渔业可持续发展重点实验室，青岛266071  \n2 青岛海洋科学与技术国家实验室，海洋渔业科学与食物产出过程功能实验室,青岛266200",
        "page_idx": 0
    },
    {
        "type": "text",
        "text": "摘要：于2015年10月对獐子岛及邻近海域进行了航次调查,研究了獐子岛及邻近海域浮游植物粒级结构的空间分布特征及其环境影响因素。结果表明,秋季表层总叶绿素a $\\cdot$ 小型( $> 2 0 \\mu \\mathrm { m }$ ）、微型(2- $2 0 \\mu \\mathrm { m }$ )和微微型( $0 . 4 5 { \\ - } { - 2 } \\mu \\mathrm { m }$ 浮游植物叶绿素a浓度的范围分别为 $0 . 5 2 \\mathrm { - 1 . 2 5 , 0 . 0 3 \\mathrm { - 0 . 8 1 , 0 . 3 3 \\mathrm { - 0 . 9 1 , 0 \\mathrm { - 0 . 0 9 \\mu g / L } } } }$ ，平均叶绿素a的浓度分别为 $0 . 7 6 _ { \\times } 0 . 1 9 \\ 、 0 . 5 3 、 0 . 0 3 \\mu \\mathrm { g / L }$ ,对叶绿素a总量的贡献率分别为 $2 3 . 7 7 \\% . 7 2 . 2 6 \\%$ 和 $3 . 9 8 \\%$ ;底层总叶绿素a、小型( ${ \\tt > } 2 0 \\mu \\mathrm { m } )$ 和微型( $2 { \\stackrel {  } { - } } 2 0 \\mu \\mathrm { m } { \\dot { \\mathrm { \\Omega } } }$ )浮游植物叶绿素a浓度的范围分别为 $0 . 1 4 - 1 . 5 \\ 、 0 . 0 4 - 1 . 0 4 \\ 、 0 . 0 8 - 0 . 4 7 \\mu \\mathrm { g } / \\mathrm { L }$ ,平均叶绿素a的浓度分别为 $0 . 4 6 , 0 . 2 2 , 0 . 2 4 \\mu \\mathrm { g / L }$ ,对叶绿素a总量的贡献率分别为 $4 1 . 4 6 \\% . 5 8 . 5 0 \\%$ 。从垂直分布上来看，总叶绿素a浓度垂直变化为，表层 $>$ 底层;小型浮游植物垂直分布较为均匀；微型浮游植物垂直变化为，表层 $\\mathrm { > }$ 底层;微微型浮游植物垂直变化为,表层 $>$ 底层,且在表、底层均保持较低水平。秋季表层微型浮游植物(2- ${ \\cdot 2 0 } \\mu \\mathrm { m }$ )浓度与盐度呈正相关。底层总叶绿素a浓度与磷酸盐浓度呈正相关,小型浮游植物( $> 2 0 \\mu \\mathrm { m }$ )浓度与磷酸盐和硅酸盐浓度均表现为正相关,微型浮游植物 $( 2 { - } 2 0 \\mu \\mathrm { m } )$ )浓度与温度呈正相关。统计分析结果表明,温度、盐度、磷酸盐及硅酸盐浓度是影响獐子岛及邻近海域秋季浮游植物粒级结构变动的重要因素。",
        "page_idx": 0
    },
    {
        "type": "text",
        "text": "关键词：浮游植物;叶绿素a;粒级结构；环境因子;獐子岛",
        "page_idx": 0
    },
    {
        "type": "text",
        "text": "Size-fractionated phytoplankton and its influencing factors in autumn near Zhangzidao Island and its adjacent waters ",
        "text_level": 1,
        "page_idx": 0
    },
    {
        "type": "text",
        "text": "WU Wenguang1 ,ZHANG Jihong1,2\\* ,LIU Yi' , WANG Wei' ,LIN Fan'   \n1KeLbortofbletfeleef   \n266071,China   \n2Function Laboratoryfor Marine Fisherie ScienceandFoodProductionProcesses,Qingdao NationalLaboratoryforMarineScienceandTechnology,Qingdao   \n266200,China ",
        "page_idx": 0
    },
    {
        "type": "text",
        "text": "Abstract：A cruise was taken in October 2015 to determine phytoplankton size structure near Zhangzidao Island and adjacentwaters.The surfaceand bottom distributionof size-fractioned phytoplanktonand itscorelation with environmental factors were examined. The concentration of total chlorophyll $a$ ，microplankton ( $\\cdot > 2 0 \\mu \\mathrm { m }$ ），nanoplankton $( 2 { - } 2 0 \\mu \\mathrm { m } )$ ），and picoplankton $( 0 . 4 5 - 2 \\mu \\mathrm { m } )$ ）were measured in the surface and bottom layers.In the surface layer，the total chlorophyll $a$ （2 concentration ranged between O.52—1. $2 5 \\mu \\mathrm { g } / \\mathrm { L }$ with an average of $0 . 7 6 ~ \\mu \\mathrm { g / L }$ ．The corresponding concentration for microplankton，nanoplankton，and picoplankton were O.03—0.81，0.33—0.91，and 0— $0 . 0 9 \\mu \\mathrm { g } / \\mathrm { L }$ with averages of 0.19, 0.53，and $0 . 0 3 \\mu \\mathrm { g } / \\mathrm { L }$ ，contributing $2 3 . 7 7 \\%$ ， $7 2 . 2 6 \\%$ ，and $3 . 9 8 \\%$ of the total chlorophyll $a$ ，respectively. In the bottom layer,total chlorophyll $a$ concentration ranged between 0.14- $\\mathrm { \\cdot 1 . 5 \\mu \\mathrm { g / L } }$ with an average of $0 . 4 6 \\mu \\mathrm { g } / \\mathrm { L }$ ，which was primarily made up by microplankton and nanoplankton，which ranged between O.O4—1.O4 and 0.08— $\\mathrm { \\cdot 0 . 4 7 \\mu g / L }$ with averages of 0.22 and $0 . 2 4 ~ \\mu \\mathrm { g } / \\mathrm { L }$ ， contributing $4 1 . 4 6 \\%$ and $5 8 . 5 0 \\%$ to the total chlorophyll $a$ ，respectively.The surface chlorophyll $a$ concentration wassignificantly higherthan thatinthebotom layer.Theverticaldistributionof nanoplanktonwas homogeneous，whereas the nanoplanktonand picoplankton tended to be more abundant in the surface layer.The concentration of picoplanktonwas lowerthan thatof theothertwo sizeclases throughout theentire water column inautumn. Significantlypositive corelations were found between nanoplanktonconcentrationandsalinityin thesurface layer，using Pearson'scorrelationanalysis.Inthe bottom layer，significantlypositive corelations were foundforseveral pairsof parameters，including the total chlorophyll $a$ and phosphate concentration，microplankton and phosphate and silicate concentrations，and nanoplankton and temperature.Temperature，salinity，and phosphateand silicateconcentrations were important factors afecting the size structure of phytoplankton near Zhangzidao Island and adjacent waters. ",
        "page_idx": 0
    },
    {
        "type": "text",
        "text": "",
        "page_idx": 1
    },
    {
        "type": "text",
        "text": "Key Words: phytoplankton； chlorophyll-a； size structure；environmental factors；Zhangzidao Island",
        "page_idx": 1
    },
    {
        "type": "text",
        "text": "浮游植物是支撑海洋生态系统的基础,浮游植物的丰度、结构等特征与环境因子密不可分,同时浮游植物群落结构也一定程度反映了海洋生态环境。掌握浮游植物粒级结构的动态变化及其环境影响机制有助于了解海洋浮游生态系统的食物网结构变化以及海洋浮游植物的生物泵效率[]。研究表明,微型（2- ${ \\cdot 2 0 } \\mu \\mathrm { m }$ 和微微型( $< 2 \\mu \\mathrm { m } \\dot { }$ )浮游植物对环境因子的变化非常敏感,且在海洋浮游植物中占有非常重要的比例[2-5」,在海洋生态系统的物质循环和能量流动中起着十分重要的作用。近年来关于浮游植物粒级结构的研究日益增多,许多专家学者对渤海[6]、黄海[1.7]、东海[7-8]等海域的浮游植物粒级结构的时空分布特征及环境影响因素做了深入的研究,为深入分析各粒级浮游植物在海洋生态系统中的作用提供了科学依据。",
        "page_idx": 1
    },
    {
        "type": "text",
        "text": "浮游植物作为海洋初级生产力的主要贡献者,是海洋生态系统的能量流动和物质循环的关键环节,它是海水养殖活动的重要支撑,是滤食性贝类的主要食物之—[9-10]。獐子岛位于黄海北部外长山群岛的最南端，拥有全国最大的虾夷扇贝养殖基地,是我国唯一的虾夷扇贝国家级原良种场[9]。在滤食性贝类养殖容量的评估中,叶绿素a是极为重要的参数,但目前关于我国最大的虾夷扇贝养殖基地—獐子岛水域的研究报道较少[9]。为此,查明獐子岛海域浮游植物生物量的粒级结构及空间分布有助于了解该海域的生态系统动力过程及其微食物环作用,且能指导该海域的生物资源开发及利用。于2015年10月在獐子岛及邻近海域进行表、底层海水浮游植物粒级结构及相关环境因子的走航调查,分析了浮游植物粒级结构与相关环境因子的关系,以掌握该海域浮游植物粒级结构的分布特征及环境影响因素,为创建新型健康养殖模式及养殖容量评估提供数据支持。",
        "page_idx": 1
    },
    {
        "type": "text",
        "text": "1材料与方法",
        "text_level": 1,
        "page_idx": 1
    },
    {
        "type": "text",
        "text": "1.1调查站位",
        "text_level": 1,
        "page_idx": 1
    },
    {
        "type": "text",
        "text": "本次调查于 2015年10月在獐子岛及邻近海域进行走航调查,调查站位共计 29个,其中獐子岛海域站位20个(6#—34#）,乌蟒岛海域站位9个（41#—49#），如图1所示。",
        "page_idx": 1
    },
    {
        "type": "text",
        "text": "1.2样品采集及测定",
        "text_level": 1,
        "page_idx": 1
    },
    {
        "type": "text",
        "text": "所有站位的样品采集均参照国家《海洋监测规范》10]规定的标准水层分别采集表层、底层水样。每个站位表、底层各取水样体积为1L,依次经过国产(浙江天台华耐产,美国标准筛定制) $2 0 \\mu \\mathrm { m }$ 筛绢， $2 \\mu \\mathrm { m } , 0 . 4 5 \\mu \\mathrm { m }$ 的上海兴亚产纤维素酯微孔滤膜(CA)逐级过滤后滴加2滴饱和碳酸镁溶液,收集不同粒径的浮游植物：小型浮游植物（Microplankton， $> 2 0 \\mu \\mathrm { m }$ ）、微型浮游植物（Nanoplankton， $2 { - } 2 0 \\mu \\mathrm { m }$ ）和微微型浮游植物（Picoplankton, $0 . 4 5 { - 2 } \\mu \\mathrm { m } \\ '$ ）。每个水样3个平行，经过滤后的滤膜于 $- 2 0 \\%$ 冷冻保存并带回实验室分析。叶绿素a的测定(萃取荧光法)采用美国产Turner-Designs Trilogy 荧光仪进行测定。",
        "page_idx": 1
    },
    {
        "type": "text",
        "text": "http ://www.ecologica.cn图中数字代表站位",
        "page_idx": 1
    },
    {
        "type": "image",
        "img_path": "images/fb1960fcc9f99fbc771ae740fe47ad227704cab61b2f19603733a05f5f11a44f.jpg",
        "img_caption": [
            "图1獐子岛及邻近海域调查站位设置",
            "Fig.1The survey stations for size-fractionated chlorophyll-a in Zhangzidao Island "
        ],
        "img_footnote": [],
        "page_idx": 2
    },
    {
        "type": "text",
        "text": "",
        "page_idx": 2
    },
    {
        "type": "text",
        "text": "温度（T,Temperature）、盐度（S,Salinity） $\\cdot \\mathrm { p H }$ 等环境参数均采用美国产YSI6600 型多参数水质仪测定。总氮（TN）、硝酸盐氮（ $N \\mathrm { O } _ { 3 } ^ { - } { - } \\mathrm { N }$ ）、亚硝氮( $N \\boldsymbol { 0 } _ { 2 } ^ { - } { - } \\boldsymbol { \\mathrm { N } }$ ）、氨氮( $\\mathrm { N H } _ { 4 } ^ { + } { \\mathrm { - } } \\mathrm { N } )$ 、总磷（TP）、活性磷酸盐( $\\mathrm { P O } _ { 4 } ^ { 3 - } { \\cdot } \\mathrm { P }$ ）、硅酸盐（ $\\mathrm { S i O } _ { 3 } ^ { 2 - }$ -Si)的测定均依据《GBl7378.4—2007,海洋监测规范》第4部分：海水分析进行分析检测,DIN 为溶解无机氮( $\\mathrm { N O } _ { 3 } ^ { - } { \\bf { N } } , \\mathrm { N O } _ { 2 } ^ { - } { \\bf { - N } }$ 和 $\\mathrm { N H } _ { 4 } ^ { + }$ -N 三者之和）,本文所测营养盐浓度均为： $\\mu \\mathrm { m o l / L }$ 。",
        "page_idx": 2
    },
    {
        "type": "text",
        "text": "1.3 数据处理",
        "text_level": 1,
        "page_idx": 2
    },
    {
        "type": "text",
        "text": "实验数据采用 Microsoft Excel 2010和 SPSS 17.0软件进行统计学分析，ANOVA单因子方差分析检验组间差异,Pearson 相关分析检验分级叶绿素 $\\overline { { \\textbf { a } } }$ 与环境因子回归关系显著性。",
        "page_idx": 2
    },
    {
        "type": "text",
        "text": "2结果与分析",
        "text_level": 1,
        "page_idx": 2
    },
    {
        "type": "text",
        "text": "2.1 环境参数",
        "text_level": 1,
        "page_idx": 2
    },
    {
        "type": "text",
        "text": "獐子岛及邻近海域秋季表、底层环境因子见表1。整个调查海域温度平均值为 $1 7 . 4 9 ^ { \\circ } \\mathrm { C }$ ,变化范围为15.67— $1 8 . 6 4 \\mathrm { ^ { \\circ } C }$ ,总体上表、底层温度垂直分布均匀。秋季表、底层除 $\\mathrm { N O } _ { 2 } ^ { - }$ -N、DIN/P 和 Si/DIN 差异显著外,其余理化因子均差异不显著。秋季底层DIN 均值低于 $2 \\mu \\mathrm { m o l / L }$ 。",
        "page_idx": 2
    },
    {
        "type": "text",
        "text": "2.2总叶绿素a分布特征",
        "text_level": 1,
        "page_idx": 2
    },
    {
        "type": "text",
        "text": "獐子岛及邻近海域秋季表、底层总叶绿素a浓度如图2所示。表层总叶绿素a浓度均值为 $( 0 . 7 6 { \\scriptstyle \\pm 0 . 1 8 } )$ $\\mu \\mathrm { g } / \\mathrm { L }$ ,浓度范围在0.52- $\\cdot 1 . 2 5 \\mu \\mathrm { g } / \\mathrm { L }$ ;而底层均值为 $( 0 . 4 6 { \\pm } 0 . 3 0 ) \\mu \\mathrm { g / L }$ ,浓度范围在0.14— $\\mathrm { \\cdot 1 . 5 \\mu g / L }$ 。从垂直分布上看，表层总叶绿素a浓度显著高于底层( $P { < } 0 . 0 5 )$ 。从水平分布上看(图2），表层高值区出现在獐子岛西北部及乌蟒岛东南部海域,低值区出现在獐子岛东北部海域;底层高值区出现在乌蟒岛北部海域,低值区出现在獐子岛东北部及乌蟒岛南部海域。",
        "page_idx": 2
    },
    {
        "type": "text",
        "text": "2.3分级叶绿素a分布特征",
        "text_level": 1,
        "page_idx": 2
    },
    {
        "type": "text",
        "text": "2.3.1小型浮游植物叶绿素a",
        "text_level": 1,
        "page_idx": 2
    },
    {
        "type": "text",
        "text": "獐子岛及邻近海域秋季表、底层小型浮游植物 $\\mathrm { \\Phi } > 2 0 \\mu \\mathrm { m } \\dot { }$ )叶绿素a浓度如图3所示。表层小型浮游植物（ $> 2 0 \\mu \\mathrm { m }$ )叶绿素a浓度均值为 $( 0 . 1 9 { \\scriptstyle \\pm 0 . 1 5 } ) \\mu \\mathrm { g / L }$ ,浓度范围在 $0 . 0 3 { \\ - } 0 . 8 1 \\mu \\mathrm { g / L }$ ;而底层均值为 $( 0 . 2 2 { \\scriptstyle \\pm 0 . 2 4 } )$ （204号$\\mu \\mathrm { g / L }$ ,浓度范围在 $( 0 . 0 4 { - } 1 . 0 4 ) \\mu \\mathrm { g / L } _ { \\alpha }$ ，从垂直分布上看，表层小型浮游植物( $> 2 0 \\mu \\mathrm { m }$ )叶绿素a浓度略低于底层，但差异不显著( $( P { > } 0 . 0 5 )$ 。从水平分布上看（图3）,表层高值区出现在獐子岛西北部及乌蟒岛北部海域，低值区出现在獐子岛东北部海域;底层高值区出现在乌蟒岛北部海域,低值区出现在獐子岛东北部及乌蟒岛",
        "page_idx": 2
    },
    {
        "type": "text",
        "text": "南部海域。",
        "page_idx": 3
    },
    {
        "type": "table",
        "img_path": "images/95ad2d3bdc59748a1572cb1ebb3ac82e45c0d07a05cfe795d227b5093757c491.jpg",
        "table_caption": [
            "表1獐子岛及邻近海域秋季相关环境理化因子",
            "Table1 The physical and chemical factors in autumn in Zhangzidao Island "
        ],
        "table_footnote": [
            "TN：总氮,Total nitrogen；TP：总磷，Total phosphorus；DIN：溶解无机氮,Disolved inorganicnitrogen；表中相同处理之间带有不同字母的数据表示相互之间差异显著"
        ],
        "table_body": "<html><body><table><tr><td rowspan=\"2\">理化因子 Physical and chemical factors</td><td colspan=\"2\">表层 Surface layer</td><td colspan=\"3\">底层 Bottom layer</td></tr><tr><td>平均值 Mean value</td><td>范围Range</td><td>平均值 Mean value</td><td></td><td>范围Range</td></tr><tr><td>温度T/C</td><td>17.49±0.59a</td><td>16.40—18.61</td><td>17.49±0.73a</td><td>15.64—18.64</td></tr><tr><td>盐度S/%0</td><td>32.09±0.38a</td><td>31.70—33.03</td><td>31.91±0.13a</td><td>31.73- 32.15</td></tr><tr><td>pH</td><td>8.01±0.14a</td><td>7.50—8.15</td><td>8.05±0.15a</td><td>7.41—8.30</td></tr><tr><td>总氮 TN/(mol/L)</td><td>193.96±58.65a</td><td>53.17—342.94</td><td>207.36±52.32a</td><td>58.04- -308.85</td></tr><tr><td>总磷 TP/(mol/L)</td><td>1.78±0.99a</td><td>0.42—3.66</td><td>2.05±1.42a</td><td>0.47—7.44</td></tr><tr><td>硝酸盐 NO3-N/(mol/L)</td><td>0.03±0.002a</td><td>0.028-0.036</td><td>0.03±0.002a</td><td>0.027-0.035</td></tr><tr><td>亚硝酸盐 NO2-N/(mol/L)</td><td>0.60±0.56a</td><td>0.01—2.08</td><td>0.18±0.24b</td><td>0.01 -0.98</td></tr><tr><td>铵盐NH4-N/(mol/L)</td><td>0.90±0.59a</td><td>0.03-2.29</td><td>0.94±0.55a</td><td>0.06- -2.00</td></tr><tr><td>溶解无机氮 DIN/(mol/L)</td><td>2.16±0.95a</td><td>0.07- -20.00</td><td>1.15±0.67a </td><td>0.14- -2.59</td></tr><tr><td>溶解无机磷 PO--P/(mol/L)</td><td>0.42±0.25a</td><td>0.03- -0.87</td><td>0.45±0.26a</td><td>0.03- -0.99</td></tr><tr><td>溶解硅 SiO²-Si/(mol/L)</td><td>11.91±4.78a</td><td>4.21- -23.56</td><td>12.40±4.35a</td><td>2.23- -23.05</td></tr><tr><td>氮磷比(DIN/P)/(mol/L)</td><td>10.73± 17.38a</td><td>0.27- -60.18</td><td>4.72±7.57b</td><td>0.31—40.95</td></tr><tr><td>氮硅比(DIN/Si)/(mol/L)</td><td>0.20±0.26a</td><td>0.01 -1.42</td><td>0.10±0.06b</td><td>0.01—0.25</td></tr><tr><td>硅磷比(Si/P)/(mol/L)</td><td>43.88±47.02a</td><td>5.84- 193.49</td><td>42.09±38.81a</td><td>3.58-165.67</td></tr></table></body></html>",
        "page_idx": 3
    },
    {
        "type": "image",
        "img_path": "images/55808bec54d5a90695fb65cf574ee914a099dbdb856add888f74881792c3cb81.jpg",
        "img_caption": [
            "图2獐子岛海域秋季表层和底层总叶绿素a浓度"
        ],
        "img_footnote": [],
        "page_idx": 3
    },
    {
        "type": "text",
        "text": "Fig.2The chlorophyll-a of surface and bottom layer in autumn in Zhangzidao Island ",
        "page_idx": 3
    },
    {
        "type": "image",
        "img_path": "images/6ec2cf05ee4b2c906c0339ad458339c9f1ffe1132699b8e03b75e172f66b5307.jpg",
        "img_caption": [
            "图3獐子岛海域秋季表层和底层小型浮游植物( $> 2 0 \\mu \\mathrm { m }$ )叶绿素a浓度"
        ],
        "img_footnote": [],
        "page_idx": 3
    },
    {
        "type": "text",
        "text": "Fig.3The microphytoplankton chlorophyll-a of surface and bottm layer inautumn in Zhangzidao Island ",
        "page_idx": 3
    },
    {
        "type": "text",
        "text": "2.3.2微型浮游植物叶绿素a",
        "text_level": 1,
        "page_idx": 4
    },
    {
        "type": "text",
        "text": "獐子岛及邻近海域秋季表、底层微型浮游植物 $( 2 { - } 2 0 \\mu \\mathrm { m } )$ 叶绿素a浓度如图4所示。表层微型浮游植物(2 ${ \\cdot 2 0 } \\mu \\mathrm { m }$ )叶绿素a浓度均值为 $( 0 . 5 3 { \\scriptstyle \\pm 0 . 1 1 } ) { \\scriptstyle \\mu \\mathrm { g / L } }$ ,浓度范围在 $0 . 3 3 { \\ - } 0 . 9 1 \\mu \\mathrm { g / L }$ ;而底层均值为 $( 0 . 2 4 { \\scriptstyle \\pm 0 . 0 9 } )$ （20$\\mu \\mathrm { g } / \\mathrm { L }$ ,浓度范围在 $( 0 . 0 8 { - } 0 . 4 7 ) \\mu \\mathrm { g / L } .$ 。从垂直分布上看，表层微型浮游植物 $( 2 { - } 2 0 \\mu \\mathrm { m } )$ )叶绿素a浓度显著高于底层。从水平分布上看(图4),表层高值区出现在獐子岛西南部及乌蟒岛东南部海域,低值区出现在乌蟒岛西北部海域;底层高值区出现在獐子岛中部及乌蟒岛西北部海域,低值区出现在獐子岛西南部海域。",
        "page_idx": 4
    },
    {
        "type": "image",
        "img_path": "images/7973cd28121147187d2ea59e4aaa5c7dfaabfa1f2fd1d513fc3ad7cc3b01eae3.jpg",
        "img_caption": [
            "图4獐子岛海域秋季表层和底层微型浮游植物(2—20μm)叶绿素a浓度"
        ],
        "img_footnote": [],
        "page_idx": 4
    },
    {
        "type": "text",
        "text": "2.3.3微微型浮游植物叶绿素a",
        "text_level": 1,
        "page_idx": 4
    },
    {
        "type": "text",
        "text": "獐子岛及邻近海域秋季表层微微型浮游植物 $( 0 . 4 5 - 2 \\mu \\mathrm { m } )$ )叶绿素a浓度如图5所示。表层微微型浮游植物 $( 0 . 4 5 - 2 \\mu \\mathrm { m } )$ 叶绿素a浓度均值为 $( 0 . 0 3 { \\scriptstyle \\pm 0 . 0 3 } ) ~ \\mathrm { \\mu g / L }$ ,浓度范围在0一 ${ \\bf \\cdot 0 . 0 9 \\mu g / L }$ ;秋季底层仅41#检测出微微型浮游植物,浓度为 $0 . 0 2 \\mu \\mathrm { g } / \\mathrm { L }$ ,其余站位底层水样中均未检测出微微型浮游植物叶绿素a浓度,鉴于此,未给出獐子岛秋季底层微微型浮游植物水平分布图。从垂直分布上看,表层微微型浮游植物 $( 0 . 4 5 - 2 \\mu \\mathrm { m }$ 叶绿素a浓度显著高于底层( $P { < } 0 . 0 5 )$ 。从水平分布上看(图5），表层高值区出现在乌蟒岛西北部海域,低值区出现在獐子岛东部海域。 0",
        "page_idx": 4
    },
    {
        "type": "text",
        "text": "2.4分级叶绿素a贡献率",
        "text_level": 1,
        "page_idx": 4
    },
    {
        "type": "text",
        "text": "獐子岛及邻近海域秋季浮游植物不同粒级的贡献率见图6。表层小型、微型和微微型浮游植物粒级叶绿素a对叶绿素a总量的平均贡献率分别为 $2 3 . 7 7 \\%$ 、$7 2 . 6 6 \\%$ 和 $3 . 9 8 \\%$ ，范围分别为： $5 . 3 6 \\% - 6 4 . 8 0 \\%$ ，$3 4 . 4 0 \\%$ 一 $9 4 . 5 5 \\% , 0 \\% - 1 5 . 3 8 \\%$ 。表层3种粒级叶绿素a对总量叶绿素a的贡献率顺序为：微型 $>$ 小型 $>$ 微微型。底层小型、微型和微微型浮游植物粒级叶绿素a对叶绿素a总量的平均贡献率分别为 $4 1 . 4 6 \\% . 5 8 . 5 0 \\%$ 和$0 . 0 5 \\%$ ，范围分别为：16. $67 \\%$ —74. $2 4 \\%$ ，25. $76 \\%$ 一$8 3 . 3 3 \\%$ ，0 $4 . 7 6 \\%$ 。底层3种粒级叶绿素a对总量叶绿素a的贡献率顺序为：微型 $>$ 小型 $>$ 微微型。獐子岛及邻近海域秋季微型和小型浮游植物占据主导地位。",
        "page_idx": 4
    },
    {
        "type": "text",
        "text": "2.5分级叶绿素a影响因素",
        "text_level": 1,
        "page_idx": 4
    },
    {
        "type": "image",
        "img_path": "images/377a8783223e753a66f369b98942a740c33bd7a5f5a187be7f9a4967da5e5361.jpg",
        "img_caption": [
            "Fig.4The nanophytoplankton chlorophyll-a of surface and bottom layer in autumn in Zhangzidao Island ",
            "图5獐子岛海域秋季表层和底层微微型浮游植物(0.45— $2 \\mu \\mathrm { m }$ ） 叶绿素a浓度 Fig.5The picophytoplankton chlorophyll-a of surface and bottom layer in autumn in Zhangzidao Island "
        ],
        "img_footnote": [],
        "page_idx": 4
    },
    {
        "type": "text",
        "text": "Pearson相关分析显示（表2）,獐子岛及邻近海域秋季表层微型浮游植物（2一 ${ \\cdot 2 0 } \\mu \\mathrm { m }$ )叶绿素a浓度与盐度呈正相关。而底层总叶绿素a浓度与磷酸盐浓度呈正相关，小型浮游植物( $> 2 0 \\mu \\mathrm { m }$ )浓度与磷酸盐和硅酸盐浓度均表现为正相关,微型浮游植物（2一 ${ \\cdot 2 0 } \\mu \\mathrm { m }$ )浓度与温度呈正相关，而微微型浮游植物 $( 0 . 4 5 - 2 \\mu \\mathrm { m }$ 浓度与硅酸盐浓度呈正相关。",
        "page_idx": 4
    },
    {
        "type": "text",
        "text": "http ://www.ecologica.cn ",
        "page_idx": 4
    },
    {
        "type": "text",
        "text": "O >20μm 2—20μm A 0.45—2μm 100.00 100.00 表层 图 底层 e 80.00 : 图 80.00 四四四 业 图 公 图 图 。 W 。 四四 。 60.00 图 图 图 图 60.00 图 O 图 。 40.00 。 0 。 40.00 。 oo 图 0 80 oo 0 。 图 图 20.00 88 8 。 oo 。 20.00 。 。。 0 A A AA A A A L 0 A AAWWAAA A A A 0 0.5 1.0 1.5 0 0.5 1.0 1.5 2.0 叶绿素a浓度 Chlorophyll-a concentration/ $( \\mu \\mathrm { g } / \\mathrm { L } )$ （20 ",
        "page_idx": 5
    },
    {
        "type": "text",
        "text": "Fig.6Thecontributionrateof diferent sized chlorophyll-aofsurface and bottomlayer inautumn in Zhangzidao Island ",
        "page_idx": 5
    },
    {
        "type": "table",
        "img_path": "images/8c18772a2b7bd29b9aa0a14515d1867000b0d180552b1ffd7ff984df64190886.jpg",
        "table_caption": [
            "Table 2Pearson correlationanalysis between Chlorophylla and environmental factors in autumn in Zhangzidao Island "
        ],
        "table_footnote": [
            "TN：总氮，Totalnitrogen；TP：总磷，Total phosphorus；DIN：溶解无机氮，Disolved inorganic nitrogen；\\*表示差异显著，\\*\\*表示差异极显著"
        ],
        "table_body": "<html><body><table><tr><td>水层 Water layer</td><td>粒级 Fraction</td><td>温度 T</td><td>盐度 S</td><td>pH</td><td>总氮 TN</td><td>总磷</td><td>溶解无机氮 DIN</td><td>溶解无机磷 PO4--P</td><td>溶解硅 SiO²−-Si</td></tr><tr><td>表层</td><td>总叶绿素a</td><td>0.122</td><td>0.101</td><td>-0.206</td><td>0.185</td><td>TP -0.098</td><td>0.161</td><td>0.188</td><td>-0.146</td></tr><tr><td>Surface layer</td><td>>20μm</td><td>0.152</td><td>-0.123</td><td>-0.162</td><td>0.074</td><td>0.142</td><td>0.054</td><td>0.352</td><td>0.008</td></tr><tr><td rowspan=\"3\"></td><td>2—20μm</td><td>-0.080</td><td>0.378 *</td><td>-0.111</td><td>0.239</td><td>-0.320</td><td>0.272</td><td>-0.244</td><td>-0.260</td></tr><tr><td>0.45—2μm</td><td>0.279</td><td>-0.147</td><td>-0.013</td><td>-0.145</td><td>-0.1791</td><td>-0.351</td><td>-0.179</td><td>0.022</td></tr><tr><td>总叶绿素a</td><td>0.346</td><td>-0.131</td><td>0.231</td><td>0.116</td><td>0.046</td><td>0.288</td><td>0.541**</td><td>0.348</td></tr><tr><td>底层 Bottom layer</td><td>>20μm</td><td>0.280</td><td>-0.132</td><td>0.180</td><td>0.111</td><td>0.100</td><td>0.292</td><td>0.555 **</td><td>0.441 *</td></tr><tr><td rowspan=\"3\"></td><td>2—20μm</td><td>0.396 *</td><td>-0.085</td><td>0.276</td><td>0.098</td><td>-0.105</td><td>0.171</td><td>0.322</td><td>-0.025</td></tr><tr><td>0.45—2μm</td><td>0.205</td><td>-0.069</td><td>0.310</td><td>-0.125</td><td>-0.143</td><td>0.347</td><td>0.164</td><td>0.427 *</td></tr><tr><td></td><td></td><td></td><td></td><td></td><td></td><td></td><td></td><td></td></tr></table></body></html>",
        "page_idx": 5
    },
    {
        "type": "text",
        "text": "3讨论",
        "text_level": 1,
        "page_idx": 5
    },
    {
        "type": "text",
        "text": "3.1浮游植物粒级结构的分布特征",
        "text_level": 1,
        "page_idx": 5
    },
    {
        "type": "text",
        "text": "獐子岛海域位于黄海北部外长山群岛的最南端,属于温带海域。相关研究表明,浮游植物粒级结构中粒径较大的小型 $( > 2 0 \\mu \\mathrm { m } )$ 和微型(2- ${ \\cdot 2 0 } \\mu \\mathrm { m }$ )浮游植物浓度随着纬度的升高而增加,而微微型 $( 0 . 4 5 - 2 \\mu \\mathrm { m }$ 浮游植物的浓度则随纬度的升高而减小[7-8,1-12]。本研究表明,獐子岛海域秋季小型和微型浮游植物粒级组成占主导地位，而微微型浮游植物对总量的贡献率低于 $5 . 4 5 \\%$ ,基本符合这一规律(表3）。",
        "page_idx": 5
    },
    {
        "type": "table",
        "img_path": "images/511fba321119faebbaa4e77b04c3af517ec3cd0e1995bf768c9f3437ab88da71.jpg",
        "table_caption": [
            "表2獐子岛海域秋季叶绿素a与环境因子的Pearson相关性",
            "表3不同纬度海域浮游植物粒级结构比较",
            "Table 3 Comparison on the size structure of phytoplankton in the different latitude in different periods "
        ],
        "table_footnote": [],
        "table_body": "<html><body><table><tr><td rowspan=\"2\">海域/贡献率 Waters/ contribution rate</td><td colspan=\"3\">秋季 Autumn</td><td rowspan=\"2\">参考文献 References</td></tr><tr><td>>20μm</td><td>2-20μm</td><td>< 2μm</td></tr><tr><td>大亚湾Daya bay</td><td>62.9%</td><td>18.1%</td><td>19.0%</td><td>[13]</td></tr><tr><td>东海 East China sea</td><td>19.05%</td><td>71.43%</td><td>16.67%</td><td>[1,14]</td></tr><tr><td>南黄海 South Yellow sea</td><td>20.83%</td><td>62.5%</td><td>16.7%</td><td>[1,14]</td></tr><tr><td>胶州湾 Jiaozhou bay</td><td>62%</td><td>36%</td><td>2%</td><td>[15]</td></tr><tr><td>本研究 This research</td><td>32.61%</td><td>65.38%</td><td>2.01%</td><td>1</td></tr></table></body></html>",
        "page_idx": 5
    },
    {
        "type": "text",
        "text": "宋伦等对辽东湾网采浮游植物的粒级结构研究表明,秋季浮游植物的粒径主要集中在中等粒径范围[16]张雪对獐子岛海域浮游植物群落结构研究表明,秋季浮游植物主要有优势种为具槽帕拉藻、米氏凯伦藻及硅藻类等粒径较大的藻类[17]。本航次鉴定出獐子岛及邻近海域浮游植物硅藻45 种、甲藻21种、硅鞭藻2种，优势种为具槽帕拉藻、海链藻、圆海链藻、离心列海链藻、菱形藻、斜纹藻和米氏凯伦藻等,浮游植物总丰度为7.5个/ $\\mathrm { \\dot { \\ m L } }$ ,其中硅藻丰度为6.9个/ $\\mathrm { \\dot { \\ m L } }$ ,甲藻丰度为0.6个/ $\\mathrm { \\dot { \\ m L } }$ ,硅藻类占优势地位（待发表数据）。而本研究表明,獐子岛及邻近海域秋季小型( $\\zeta > 2 0 \\mu \\mathrm { m }$ )和微型浮游植物（2- $2 0 \\mu \\mathrm { m }$ )的平均贡献率分别为 $3 2 . 6 2 \\%$ 和$6 5 . 3 8 \\%$ ,占据优势地位,且对该季节浮游植物优势种鉴定发现,较大粒级的硅藻类[17]占据优势地位,与以上研究结果相一致,进一步说明在温度较低的冷水海域中,粒级较大的浮游植物( $> 2 0 \\mu \\mathrm { m }$ 和2- ${ \\cdot 2 0 } \\mu \\mathrm { m }$ )的比例相应较高[15]。",
        "page_idx": 6
    },
    {
        "type": "text",
        "text": "北黄海海域的生态环境受到大陆气候、黄海暖流、陆源冲淡水和季节性冷水团的影响,其浮游植物群落结构呈现出不同的区系分布特征[16-18]。王俊研究表明,低盐、高营养的渤海沿岸水与高盐、低营养的黄海水导致浮游植物高度分布不均匀[19-20]。许澄源研究表明,辽南沿岸流包括鸭绿江、大洋河、庄河、碧流河等大量径流入海,给长海县海域增添了一部分营养盐,使之呈现由北向南递减之势[2]。本研究表明,总叶绿素a及3种粒级浮游植物浓度的表、底层空间分布趋势相近,高值区均出现在乌蟒岛海域,低值区均出现在獐子岛南部海域,且表层高于底层,乌蟒岛海域地理位置靠北,其温度和营养盐水平整体高于獐子岛海域(表4),从而引起其浮游植物叶绿素a浓度水平高于獐子岛海域,说明温度和营养盐是影响獐子岛及邻近水域浮游植物粒级空间分布的重要因素。",
        "page_idx": 6
    },
    {
        "type": "table",
        "img_path": "images/bcd183de71d277f57686cef48c724e079d4a3e745300e27e71fc4b60260d7e6b.jpg",
        "table_caption": [
            "表4獐子岛及邻近海域秋季相关环境理化因子",
            "Table 4The physical and chemical factors in autumn in Zhangzidao Island "
        ],
        "table_footnote": [
            "DIN：溶解无机氮，Disslved inorganic nitrogen;表中相同处理之间带有不同字母的数据表示相互之间差异显著"
        ],
        "table_body": "<html><body><table><tr><td rowspan=\"2\">理化因子 Physical and chemical factors</td><td colspan=\"2\">獐子岛海域 Zhangzidao island</td><td colspan=\"2\">乌蟒岛海域 Wumang island</td></tr><tr><td>表层 Surface layer</td><td>底层 Bottom layer</td><td>表层 Surface layer</td><td>底层 Bottom layer</td></tr><tr><td>温度T</td><td>17.25±0.41a</td><td>17.10±0.52a</td><td>18.01±0.60b</td><td>18.35±0.17b</td></tr><tr><td>盐度S</td><td>32.11±0.34a</td><td>31.96±0.12a</td><td>32.03±0.48a</td><td>31.80±0.04a</td></tr><tr><td>溶解无机氮DIN</td><td>2.83±4.12a</td><td>1.09±0.66b</td><td>0.68±0.70c</td><td>1.31±0.72b</td></tr><tr><td>溶解无机磷PO-P</td><td>0.36±0.25a</td><td>0.36±0.24a</td><td>0.55±0.19b</td><td>0.65±0.20b</td></tr><tr><td>溶解硅 SiO²-Si</td><td>11.04±4.15a</td><td>11.52±1.97a</td><td>13.85±5.74b</td><td>14.35±7.14b</td></tr></table></body></html>",
        "page_idx": 6
    },
    {
        "type": "text",
        "text": "3.2浮游植物粒级结构的影响因素",
        "text_level": 1,
        "page_idx": 6
    },
    {
        "type": "text",
        "text": "海水中的营养盐浓度通常是浮游植物生长的重要限制因子,营养盐浓度的高低很大程度上调控着浮游植物生物量的粒级结构及其分布。已有研究表明,温度、盐度、营养盐浓度以及浮游动物摄食是决定浮游植物粒级结构组成的关键环境因子[23]。其中营养盐对于浮游植物群落结构的影响是迅速和灵敏的[24]。 $\\mathrm { ~ N ~ } , \\mathrm { ~ P ~ } , \\mathrm { ~ S i ~ }$ 是海洋浮游植物生长必不可少的营养盐,由于不同海区的状况不同,以上几项营养盐都有可能成为浮游植物生长的限制因子[23]。本研究结合Fisher等和Justic 等提出的两种方法来判断獐子岛及邻近海域的浮游植物是否受到营养盐的限制[22,25-26],獐子岛及邻近海域秋季底层 $\\scriptstyle \\mathrm { D I N } < 2 \\mu \\mathrm { m o l } \\ / \\mathrm { L }$ ，且 $\\mathrm { D I N } / \\mathrm { P } { < } 1 0 , \\mathrm { S i } / \\mathrm { N } { > } 1$ (表1),结果表明獐子岛及邻近海域秋季底层营养盐存在氮限制,无机氮是影响獐子岛秋季浮游植物生长和群落结构的主要因子,与王勇和焦念志[27],张继红等[9]研究结果相一致。",
        "page_idx": 6
    },
    {
        "type": "text",
        "text": "T 浮游植物粒级结构的分布与水域中被其直接利用的营养盐的含量分布和变化密切相关。从营养盐水平分析来看,獐子岛水域常年属于国家一类海水水质标准,多数时间属贫营养水平[9],磷酸盐浓度低于国家一类水质标准且 $\\mathrm { S i } / \\mathrm { P } = 4 3 { > } 2 2$ ，存在磷元素潜在限制,本研究结果显示秋季底层总叶绿素a浓度以及小型浮游植物( ${ \\tt > } 2 0 \\mu \\mathrm { m } \\dot { \\bf { \\mu } }$ )浓度与磷酸盐浓度均表现为正相关,表明磷酸盐可能成为秋季小型浮游植物( $> 2 0 \\mu \\mathrm { m }$ )生长的限制因子。张雪等研究结果表明,秋季獐子岛海域底层浮游植物优势种主要为硅藻、甲藻和金藻,各占6种、2种和1种,其中硅藻占优势地位[17],而硅酸盐是硅藻的必需营养元素[28],硅藻喜低温,最适合的温度通常低于 $1 8 ^ { \\circ } \\mathrm { C }$ [29],而本研究表明底层小型浮游植物 $( > 2 0 \\mu \\mathrm { m } )$ )浓度与硅酸盐浓度呈正相关,表明硅酸盐可能成为影响秋季獐子岛海域小型浮游植物( $> 2 0 \\mu \\mathrm { m }$ )生长的重要因子。",
        "page_idx": 6
    },
    {
        "type": "text",
        "text": "",
        "page_idx": 7
    },
    {
        "type": "text",
        "text": "浮游植物的粒级结构除主要受营养盐的上行效应影响之外，大规模养殖滤食性贝类及浮游动物大量摄食的下行效应也能对浮游植物的粒级结构产生较大压力[9,30-31]。张雪[17]对獐子岛秋季底播虾夷扇贝胃含物的浮游植物种类组成研究发现,优势种为具槽帕拉藻、圆筛藻、海链藻、曲舟藻、辐射圆筛藻和小等刺硅鞭藻,其中具槽帕拉藻的优势度显著高于其他种类。McQuoid 等对具槽帕拉藻的粒径研究表明,其粒径范围在 8—$4 8 \\mu \\mathrm { m }$ ，而 $1 0 { - } 1 8 \\mu \\mathrm { m }$ 范围的藻细胞占据了优势地位[32],李扬对海链藻与圆筛藻的形态学比较研究表明,绝大多数海链藻种类的细胞直径在3- ${ \\cdot 2 0 } \\mu \\mathrm { m }$ ,而圆筛藻的细胞直径变化范围较大,大部分范围集中在40—100μm之间[33]。而本研究结果表明,秋季底层总叶绿素a浓度低于表层,底层微型（2一 ${ \\cdot 2 0 } \\mu \\mathrm { m }$ )浮游植物浓度显著低于表层,且表层微型 $( 2 { - } 2 0 \\mu \\mathrm { m }$ )浮游植物的贡献率( $7 2 . 6 6 \\%$ )显著高于底层( $5 8 . 5 0 \\%$ ）,秋季的水温处于虾夷扇贝生长的最适温度范围内,其摄食、生长的能力强9,由此推测,獐子养殖水域虾夷扇贝摄食的下行效应可能是影响该海域秋季底层浮游植物粒级结构变化的重要因素。",
        "page_idx": 7
    },
    {
        "type": "text",
        "text": "致谢：感谢獐子岛集团赵学伟经理及“辽长渔科研19\"号全体船员在航次调查和样品采集中给予的帮助。",
        "page_idx": 7
    },
    {
        "type": "text",
        "text": "参考文献（References）：",
        "text_level": 1,
        "page_idx": 7
    },
    {
        "type": "text",
        "text": "[1］傅明珠，孙萍，王宗灵，李艳，李瑞香.黄海冷水团水域浮游植物群落粒级结构的季节变化.海洋学报，2010，32（1)：120-129.  \n2]TkaasefangK.zeucueofplaoasdoosisibroicalantesrie6(2):203-211.  \n3]Kos，siVefoaostisaloGl,Greece）.Helgoland Marine Research，2002,56(2）：125-133  \n[4］刘诚刚，宁修仁，孙军，蔡昱明，曹建平.2002年夏季南极普里兹湾及其邻近海域浮游植物现存量、初级生产力粒级结构和新生产力研究.海洋学报，2004，26(6)：107-117.  \n[5］蔡昱明，宁修仁，朱根海，史君贤.南极普里兹湾浮游植物现存量与初级生产力粒级结构和新生产力研究.海洋学报，2005，27（4)：135- 147.  \n［6］邹芳睿.渤海湾分级叶绿素对营养盐浓度变化的响应.天津：天津大学，2009：14-32.  \n[7］邓春梅，于志刚，姚鹏，陈洪涛，薛春勇.东海 南黄海浮游植物粒级结构及环境影响因素分析.中国海洋大学学报，208，38（5）：791-798, 756.  \n[8］孙晓霞，任琳琳，郑珊，文斐，赵永芳，孙松.2011年春夏季黄、东海浮游植物粒级结构.海洋与湖沼，2012,43（3）：419-428.  \n[9］张继红，方建光，蒋增杰，王巍，王诗欢，孙松.獐子岛养殖水域叶绿素含量时空分布特征及初级生产力季节变化.海洋水产研究，2008，29(4) : 22-28.  \n[10]郝林华，孙丕喜，郝建民，杜蓓蓓，张新军，徐玉珊，毕进红.桑沟湾海域叶绿素a的时空分布特征及其影响因素研究.生态环境学报，2012,21(2) : 338-345.  \n[11]AgawinNSR，DuarteCM，AgstS.Nutrientandtemperaturecontrooftecontributionofpicoplanktotphytoplnktonboasndproduction. Limnology and Oceanography，2000,45（3）: 591-600.  \n[12] AndersonA，HackyP,HagstrAEfetoftemperatureadligtotegrowthof-Nanandplankto:impactolgleioMarine Biology，1994，120(4）：511-520.  \n[13] 李丽，江涛，吕颂辉.大亚湾海域夏、秋季分粒级叶绿素a分布特征.海洋环境科学，2013,32(2)：185-189.  \n[14] 黄邦钦，刘媛，陈纪新，王大志，洪华生，吕瑞华，黄凌风，林以安，魏皓.东海、黄海浮游植物生物量的粒级结构及时空分布.海洋学报，2006,28(2)：156-164.  \n[15] 孙晓霞，孙松.胶州湾浮游植物粒级结构及其时空变化.海洋与湖沼，2012，43（3)：411-418.  \n[16]宋伦，宋广军，王年斌，赵海勃，田金，杨爽，杜静.辽东湾网采浮游植物粒级结构的胁迫响应.中国环境科学，2015，35（9)：2764- 2771.  \n[17］张雪.獐子岛邻近水域浮游植物群落结构及其与虾夷扇贝（Patinopecten yesoensis)食性关系的研究.上海：上海海洋大学，2013：8-69.  \n[18] 郭世鑫.近百年来北黄海浮游植物生产力和种群结构变化的生物标志物记录及影响因素.青岛：中国海洋大学，2015：3-54.  \n[19］王俊.黄海春季浮游植物的调查研究.海洋水产研究，2001,22(1)：56-61.  \n[20］王俊.黄海秋、冬季浮游植物的调查研究.海洋水产研究，2003，24(1)：15-23.  \n[21］许澄源.辽宁省长海县近海生态特点与渔业.水产科学，1985，4(1)：32-36.  \n22JustiDbaErthtfaits consequences.Estuarine，Coastal and Shelf Science，1995，40(3）：339-356.  \n23]UyeSepctofeopdsalwioatiobusedse.l(1):513-519.  \n[24] 王资生.海水营养盐及其对浮游植物的影响.盐城工学院学报，2001，14(2)：40-43，49.  \n[25]FisherTR，PelelER，AmmeanJW,HardingLWJr.NutrientliitatonofpytoplanktoninChsapeakeBayMarieEcolgreSeries，1992,82(1):51-63.  \n［26］吴文广，张继红,王巍，房景辉，刘毅，牛亚丽，高振锟.桑沟湾水域叶绿素a在海带收获前后的变化及其影响因素.水产学报,2015，39(8):1178-1186.  \n[27] 王勇，焦念志.北黄海浮游植物营养盐限制的初步研究.海洋与湖沼，1999，30(5)：512-518.  \n[28] 梁君荣，陈丹丹，高亚辉，程金凤.海洋硅藻硅质细胞壁结构的形成机理研究概述.海洋学报，2010，32（5）：1-8.  \n[29] Wasmund,ialaJanSdepitbrsiaoosiiietSea.Journal of Marine Systems，2011,87(2）：145-159.  \n[30] Dame RF,Prins T C. Bivalve carrying capacity in coastal ecosystems. Aquatic Ecology，1997,31(4): 409-421.  \n31SalAasJlSciences，2001,58(5）:991-1002.  \n[32]McQuoid,drgKedatoPraliatviotaliatorspesinastaledientsstarnoastaldefScience，2003，56(2):339-354.  \n[33］李扬.海链藻（Thalasiosira)）与圆筛藻（Coscinodiscus）的形态学比较研究.植物研究，2009，29（3）：282-288.",
        "page_idx": 7
    },
    {
        "type": "text",
        "text": "",
        "page_idx": 8
    }
]